Workbook

Sheet Inputs
A1: Reddit IPO Pricing Review — Inputs
A2: Blue = imported source input; green elsewhere = formula. USD mm / mm shares unless noted.
A4: Key | B4: Value | C4: Unit | D4: Fact type | E4: Policy | F4: Source path / cell | G4: Notes
A5: Revenue_2022A | B5: 666.701 | C5: USD mm | D5: SEC public fact | E5: CP-02 | F5: /app/input_files/sec_filings/SEC-01_financials_extract.xlsx::'Public_Financials'!B2 | G5: Authoritative FY2022 tie-out target
A6: Revenue_2023A | B6: 804.029 | C6: USD mm | D6: SEC public fact | E6: CP-02/06 | F6: /app/input_files/sec_filings/SEC-01_financials_extract.xlsx::'Public_Financials'!C2 | G6: Audited historical revenue
A7: Growth_2024E | B7: 0.22 | C7: % | D7: Internal committee assumption | E7: CP-06 | F7: /app/input_files/committee/Underwriting_Assumptions_20240320.xlsx::'Assumptions'!B2 | G7: Not an SEC fact
A8: Mgmt_Adj_EBITDA | B8: -69.275 | C8: USD mm | D8: SEC-disclosed management non-GAAP | E8: CP-03 | F8: /app/input_files/sec_filings/SEC-01_financials_extract.xlsx::'Public_Financials'!C6 | G8: Starting point
A9: SBC | B9: 49.086 | C9: USD mm | D9: SEC public fact | E9: CP-03 | F9: /app/input_files/sec_filings/SEC-01_financials_extract.xlsx::'Public_Financials'!C7 | G9: Recurring economic cost
A10: Restructuring | B10: 8.098 | C10: USD mm | D10: SEC public fact | E10: CP-04 | F10: /app/input_files/sec_filings/SEC-01_financials_extract.xlsx::'Public_Financials'!C8 | G10: Already adjusted by management
A11: FCF | B11: -84.838 | C11: USD mm | D11: SEC public fact | E11: CP-13 | F11: /app/input_files/sec_filings/SEC-01_financials_extract.xlsx::'Public_Financials'!C10 | G11: Negative risk indicator
A12: Cash | B12: 401.176 | C12: USD mm | D12: SEC public fact | E12: CP-08 | F12: /app/input_files/sec_filings/SEC-01_financials_extract.xlsx::'Public_Financials'!C11 | G12: Net cash bridge
A13: Marketable_Securities | B13: 811.946 | C13: USD mm | D13: SEC public fact | E13: CP-08 | F13: /app/input_files/sec_filings/SEC-01_financials_extract.xlsx::'Public_Financials'!C12 | G13: Included in equity bridge
A14: Economic_Shares | B14: 143.71656 | C14: mm shares | D14: Internal committee assumption | E14: CP-02 | F14: /app/input_files/committee/Offering_Terms_20240320.xlsx::'Offering_Terms'!B6 | G14: SEC-09 components sum to same amount
A15: Multiple_Low | B15: 4 | C15: x | D15: Internal committee assumption | E15: CP-07 | F15: /app/input_files/committee/Underwriting_Assumptions_20240320.xlsx::'Assumptions'!B3 | G15: Committee peer set
A16: Multiple_Mid | B16: 4.5 | C16: x | D16: Internal committee assumption | E16: CP-07 | F16: /app/input_files/committee/Underwriting_Assumptions_20240320.xlsx::'Assumptions'!B4 | G16: Committee peer set
... A32: SEC02_Dilution | B32: 21.33 | C32: USD/share | D32: SEC public cross-check | E32: Boundary | F32: /app/input_files/sec_filings/SEC-02_dilution_crosscheck.xlsx::'Dilution_Crosscheck'!B3 | G32: Only verifies assumed price less NTBV

Sheet QoE
A1: Quality of Earnings Bridge
A2: Management non-GAAP to underwriting EBITDA; restructuring is not double-counted.
A4: Line | B4: Amount | C4: Unit | D4: Formula / treatment | E4: Policy | F4: Source | G4: Risk / note
A5: Management Adjusted EBITDA | B5: =Inputs!$B$8 -> -69.275 | C5: USD mm | D5: Starting point | E5: CP-03 | F5: /app/input_files/sec_filings/SEC-01_financials_extract.xlsx::'Public_Financials'!C6 | G5: Management-defined; not audited non-GAAP
A6: Less: SBC addback reversed | B6: =-Inputs!$B$9 -> -49.086 | C6: USD mm | D6: SBC is recurring economic cost | E6: CP-03 | F6: /app/input_files/sec_filings/SEC-01_financials_extract.xlsx::'Public_Financials'!C7 | G6: Detail TOTAL mismatch is audited separately
A7: Restructuring incremental adjustment | B7: =0 -> 0 | C7: USD mm | D7: 8.098 already in management adjustments | E7: CP-04 | F7: /app/input_files/committee/Committee_Policy_v3_20240320.xlsx::'Committee_Policy'!C5 | G7: Do not add back twice
A8: Underwriting EBITDA | B8: =SUM(B5:B7) -> -118.361 | C8: USD mm | D8: Management EBITDA − SBC + zero incremental restructuring | E8: CP-03/04 | F8: Calculated | G8: Negative; EV/EBITDA not used
A9: Free Cash Flow | B9: =Inputs!$B$11 -> -84.838 | C9: USD mm | D9: SEC definition: operating cash flow less capex | E9: CP-13 | F9: /app/input_files/sec_filings/SEC-01_financials_extract.xlsx::'Public_Financials'!C10 | G9: Negative; explicit pricing risk

Sheet Valuation
A1: EV / 2024E Revenue Valuation
A2: Underwriting EBITDA is negative, so CP-05 requires EV/2024E Revenue. Discount is applied to equity value/share.
A4: Step | B4: Low | C4: Mid | D4: High | E4: Unit / formula
A5: 2023A Revenue | B5: =Inputs!$B$6 -> 804.029 | C5: =Inputs!$B$6 -> 804.029 | D5: =Inputs!$B$6 -> 804.029 | E5: SEC public fact
A6: 2024E Growth | B6: =Inputs!$B$7 -> 0.22 | C6: =Inputs!$B$7 -> 0.22 | D6: =Inputs!$B$7 -> 0.22 | E6: Internal assumption
A7: 2024E Revenue | B7: =B5*(1+B6) -> 980.91538 | C7: =C5*(1+C6) -> 980.91538 | D7: =D5*(1+D6) -> 980.91538 | E7: 2023A × (1 + growth)
A8: EV / Revenue | B8: =Inputs!$B$15 -> 4 | C8: =Inputs!$B$16 -> 4.5 | D8: =Inputs!$B$17 -> 5 | E8: Committee multiples
A9: Enterprise Value | B9: =B7*B8 -> 3923.6615 | C9: =C7*C8 -> 4414.1192 | D9: =D7*D8 -> 4904.5769 | E9: 2024E revenue × multiple
A10: Add: Cash | B10: =Inputs!$B$12 -> 401.176 | C10: =Inputs!$B$12 -> 401.176 | D10: =Inputs!$B$12 -> 401.176 | E10: CP-08
A11: Add: Marketable Securities | B11: =Inputs!$B$13 -> 811.946 | C11: =Inputs!$B$13 -> 811.946 | D11: =Inputs!$B$13 -> 811.946 | E11: CP-08
A12: Pre-money Equity Value | B12: =SUM(B9:B11) -> 5136.7835 | C12: =SUM(C9:C11) -> 5627.2412 | D12: =SUM(D9:D11) -> 6117.6989 | E12: EV + cash + securities
A13: Economic Shares | B13: =Inputs!$B$14 -> 143.71656 | C13: =Inputs!$B$14 -> 143.71656 | D13: =Inputs!$B$14 -> 143.71656 | E13: mm shares
A14: Undiscounted Equity / Share | B14: =B12/B13 -> 35.74246 | C14: =C12/C13 -> 39.155133 | D14: =D12/D13 -> 42.567807 | E14: Equity ÷ shares
A15: IPO Execution Discount | B15: =Inputs!$B$18 -> 0.125 | C15: =Inputs!$B$18 -> 0.125 | D15: =Inputs!$B$18 -> 0.125 | E15: CP-09
A16: Discounted Value / Share | B16: =B14*(1-B15) -> 31.274653 | C16: =C14*(1-C15) -> 34.260742 | D16: =D14*(1-D15) -> 37.246831 | E16: Undiscounted/share × (1 − discount)

Sheet Sensitivity
A1: Single-Point Pricing Sensitivity
A2: Each cell independently varies growth and multiple; all other inputs remain unchanged. Base = 22% × 4.5x.
A4: Growth / Multiple | B4: 4 | C4: 4.3 | D4: 4.5 | E4: 4.8 | F4: 5 | G4: Row note
A5: 0.18 | B5: =(Inputs!$B$6*(1+$A5)*B$4+Inputs!$B$12+Inputs!$B$13)/Inputs!$B$14*(1-Inputs!$B$18) -> 30.491416 | C5: =(Inputs!$B$6*(1+$A5)*C$4+Inputs!$B$12+Inputs!$B$13)/Inputs!$B$14*(1-Inputs!$B$18) -> 32.224327 | D5: =(Inputs!$B$6*(1+$A5)*D$4+Inputs!$B$12+Inputs!$B$13)/Inputs!$B$14*(1-Inputs!$B$18) -> 33.379601 | E5: =(Inputs!$B$6*(1+$A5)*E$4+Inputs!$B$12+Inputs!$B$13)/Inputs!$B$14*(1-Inputs!$B$18) -> 35.112512 | F5: =(Inputs!$B$6*(1+$A5)*F$4+Inputs!$B$12+Inputs!$B$13)/Inputs!$B$14*(1-Inputs!$B$18) -> 36.267785 | G5: Single-point
A6: 0.2 | B6: =(Inputs!$B$6*(1+$A6)*B$4+Inputs!$B$12+Inputs!$B$13)/Inputs!$B$14*(1-Inputs!$B$18) -> 30.883034 | C6: =(Inputs!$B$6*(1+$A6)*C$4+Inputs!$B$12+Inputs!$B$13)/Inputs!$B$14*(1-Inputs!$B$18) -> 32.645316 | D6: =(Inputs!$B$6*(1+$A6)*D$4+Inputs!$B$12+Inputs!$B$13)/Inputs!$B$14*(1-Inputs!$B$18) -> 33.820171 | E6: =(Inputs!$B$6*(1+$A6)*E$4+Inputs!$B$12+Inputs!$B$13)/Inputs!$B$14*(1-Inputs!$B$18) -> 35.582453 | F6: =(Inputs!$B$6*(1+$A6)*F$4+Inputs!$B$12+Inputs!$B$13)/Inputs!$B$14*(1-Inputs!$B$18) -> 36.757308 | G6: Single-point
A7: 0.22 | B7: =(Inputs!$B$6*(1+$A7)*B$4+Inputs!$B$12+Inputs!$B$13)/Inputs!$B$14*(1-Inputs!$B$18) -> 31.274653 | C7: =(Inputs!$B$6*(1+$A7)*C$4+Inputs!$B$12+Inputs!$B$13)/Inputs!$B$14*(1-Inputs!$B$18) -> 33.066306 | D7: =(Inputs!$B$6*(1+$A7)*D$4+Inputs!$B$12+Inputs!$B$13)/Inputs!$B$14*(1-Inputs!$B$18) -> 34.260742 | E7: =(Inputs!$B$6*(1+$A7)*E$4+Inputs!$B$12+Inputs!$B$13)/Inputs!$B$14*(1-Inputs!$B$18) -> 36.052395 | F7: =(Inputs!$B$6*(1+$A7)*F$4+Inputs!$B$12+Inputs!$B$13)/Inputs!$B$14*(1-Inputs!$B$18) -> 37.246831 | G7: Base growth
A8: 0.24 | B8: =(Inputs!$B$6*(1+$A8)*B$4+Inputs!$B$12+Inputs!$B$13)/Inputs!$B$14*(1-Inputs!$B$18) -> 31.666271 | C8: =(Inputs!$B$6*(1+$A8)*C$4+Inputs!$B$12+Inputs!$B$13)/Inputs!$B$14*(1-Inputs!$B$18) -> 33.487296 | D8: =(Inputs!$B$6*(1+$A8)*D$4+Inputs!$B$12+Inputs!$B$13)/Inputs!$B$14*(1-Inputs!$B$18) -> 34.701312 | E8: =(Inputs!$B$6*(1+$A8)*E$4+Inputs!$B$12+Inputs!$B$13)/Inputs!$B$14*(1-Inputs!$B$18) -> 36.522337 | F8: =(Inputs!$B$6*(1+$A8)*F$4+Inputs!$B$12+Inputs!$B$13)/Inputs!$B$14*(1-Inputs!$B$18) -> 37.736354 | G8: Single-point
A9: 0.26 | B9: =(Inputs!$B$6*(1+$A9)*B$4+Inputs!$B$12+Inputs!$B$13)/Inputs!$B$14*(1-Inputs!$B$18) -> 32.057889 | C9: =(Inputs!$B$6*(1+$A9)*C$4+Inputs!$B$12+Inputs!$B$13)/Inputs!$B$14*(1-Inputs!$B$18) -> 33.908285 | D9: =(Inputs!$B$6*(1+$A9)*D$4+Inputs!$B$12+Inputs!$B$13)/Inputs!$B$14*(1-Inputs!$B$18) -> 35.141883 | E9: =(Inputs!$B$6*(1+$A9)*E$4+Inputs!$B$12+Inputs!$B$13)/Inputs!$B$14*(1-Inputs!$B$18) -> 36.992279 | F9: =(Inputs!$B$6*(1+$A9)*F$4+Inputs!$B$12+Inputs!$B$13)/Inputs!$B$14*(1-Inputs!$B$18) -> 38.225877 | G9: Single-point
A12: Scenario | B12: Growth | C12: Multiple | D12: Value/share | E12: Role | F12: Policy | G12: Note
A13: Low | B13: =Inputs!$B$7 -> 0.22 | C13: =Inputs!$B$15 -> 4 | D13: =Valuation!B16 -> 31.274653 | E13: Range endpoint | F13: CP-07/09 | G13: Committee support range
A14: Mid | B14: =Inputs!$B$7 -> 0.22 | C14: =Inputs!$B$16 -> 4.5 | D14: =Valuation!C16 -> 34.260742 | E14: Base | F14: CP-07/09 | G14: Committee support range
A15: High | B15: =Inputs!$B$7 -> 0.22 | C15: =Inputs!$B$17 -> 5 | D15: =Valuation!D16 -> 37.246831 | E15: Range endpoint | F15: CP-07/09 | G15: Committee support range

Sheet Offering_Proceeds
A1: Offering Structure and Company Proceeds
A2: Base excludes greenshoe. Secondary produces no company proceeds and no new company shares.
A4: Line | B4: Base | C4: Full Greenshoe | D4: Unit | E4: Formula / policy
A5: Working price | B5: =Inputs!$B$19 -> 34 | C5: =Inputs!$B$19 -> 34 | D5: USD/share | E5: Internal decision input
A6: Primary shares | B6: =Inputs!$B$20 -> 15.276527 | C6: =Inputs!$B$20+Inputs!$B$24 -> 18.576527 | D6: mm shares | E6: CP-10/11
A7: Secondary shares | B7: =Inputs!$B$22 -> 6.723473 | C7: =Inputs!$B$22 -> 6.723473 | D7: mm shares | E7: No company proceeds
A8: Greenshoe shares | B8: =0 -> 0 | C8: =Inputs!$B$24 -> 3.3 | D8: mm shares | E8: Base excluded; full exercised
A9: Total shares sold | B9: =B6+B7 -> 22 | C9: =C6+C7 -> 25.3 | D9: mm shares | E9: Primary + secondary; shoe already in full primary
A10: Company gross proceeds | B10: =B5*B6 -> 519.40192 | C10: =C5*C6 -> 631.60192 | D10: USD mm | E10: Price × primary only
A11: Underwriting fee rate | B11: =Inputs!$B$28 -> 0.05 | C11: =Inputs!$B$28 -> 0.05 | D11: % primary gross | E11: CP-12
A12: Underwriting fee | B12: =B10*B11 -> 25.970096 | C12: =C10*C11 -> 31.580096 | D12: USD mm | E12: Company primary gross × fee rate
A13: Fixed company expenses | B13: =Inputs!$B$29 -> 7 | C13: =Inputs!$B$29 -> 7 | D13: USD mm | E13: Once; not repeated for shoe
A14: Net company proceeds | B14: =B10-B12-B13 -> 486.43182 | C14: =C10-C12-C13 -> 593.02182 | D14: USD mm | E14: Gross − fee − fixed
A15: Secondary proceeds to company | B15: =0 -> 0 | C15: =0 -> 0 | D15: USD mm | E15: CP-10 / SEC-12

Sheet Dilution
A1: Share Count Bridge and Dilution
A2: New-share percentages are clearly labeled. SEC-02 is only a $32.50 cross-check and is not extrapolated to $34.
A4: Line | B4: Base | C4: Full Greenshoe | D4: Unit | E4: Formula / boundary
A5: Pre-money economic shares | B5: =Inputs!$B$14 -> 143.71656 | C5: =Inputs!$B$14 -> 143.71656 | D5: mm shares | E5: Committee economic denominator
A6: New primary shares | B6: =Inputs!$B$20 -> 15.276527 | C6: =Inputs!$B$20+Inputs!$B$24 -> 18.576527 | D6: mm shares | E6: Secondary excluded
A7: Secondary incremental shares | B7: =0 -> 0 | C7: =0 -> 0 | D7: mm shares | E7: Transfer only
A8: Post-money shares | B8: =B5+B6+B7 -> 158.99309 | C8: =C5+C6+C7 -> 162.29309 | D8: mm shares | E8: Pre-money + new primary
A9: New primary / post-money | B9: =B6/B8 -> 0.096082962 | C9: =C6/C8 -> 0.11446283 | D9: % | E9: Primary ÷ post-money
A10: New primary / pre-money | B10: =B6/B5 -> 0.10629622 | C10: =C6/C5 -> 0.12925808 | D10: % | E10: Additional disclosure; not post-money dilution
A11: SEC-02 assumed price | B11: =Inputs!$B$30 -> 32.5 | C11: — | D11: USD/share | E11: Cross-check only
A12: SEC-02 preliminary NTBV/share | B12: =Inputs!$B$31 -> 11.17 | C12: — | D12: USD/share | E12: At assumed price only
A13: SEC-02 immediate dilution | B13: =B11-B12 -> 21.33 | C13: — | D13: USD/share | E13: Assumed price − NTBV/share
A14: SEC-02 reported dilution | B14: =Inputs!$B$32 -> 21.33 | C14: — | D14: USD/share | E14: Tie-out; no $34 NTBV extrapolation
A15: SEC-02 tie-out difference | B15: =B13-B14 -> 0 | C15: — | D15: USD/share | E15: Must be zero

Sheet Pricing_Summary
A1: Pricing Committee Summary
A2: Rule: within support range, within $0.50 of midpoint, and no unresolved hard structural error.
A4: Metric / test | B4: Value | C4: Unit | D4: Result | E4: Formula / policy
A5: Support range — low | B5: =Valuation!B16 -> 31.274653 | C5: USD/share | D5: Range endpoint | E5: CP-07/09
A6: Support range — midpoint | B6: =Valuation!C16 -> 34.260742 | C6: USD/share | D6: Reference | E6: CP-07/09
A7: Support range — high | B7: =Valuation!D16 -> 37.246831 | C7: USD/share | D7: Range endpoint | E7: CP-07/09
A8: Proposed working price | B8: =Inputs!$B$19 -> 34 | C8: USD/share | D8: Decision input | E8: Not a final result
A9: Signed price − midpoint | B9: =B8-B6 -> -0.26074181 | C9: USD/share | D9: Negative = below midpoint | E9: Working price − midpoint
A10: Absolute distance to midpoint | B10: =ABS(B9) -> 0.26074181 | C10: USD/share | D10: Threshold ≤ $0.50 | E10: CP-14
A11: Test 1: within support range | B11: =AND(B8>=B5,B8<=B7) -> TRUE | C11: Boolean | D11: Required | E11: CP-14
A12: Test 2: midpoint distance ≤ $0.50 | B12: =B10<=0.5 -> TRUE | C12: Boolean | D12: Required | E12: CP-14
A13: Test 3: no unresolved hard structural error | B13: =AND(Methodology!C13:C22) -> TRUE | C13: Boolean | D13: Required | E13: Linked to named Methodology structure checks; governance exceptions are separately flagged
A14: Committee disposition | B14: =IF(AND(B11,B12,B13),"Proceed",IF(AND(B11,B13),"Reprice","Defer")) -> Proceed | C14: Decision | D14: Proceed | E14: CP-14/15; references all three tests
A15: QoE risk | B15: Underwriting EBITDA and FCF are negative | C15: Text | D15: Disclose | E15: CP-13

Sheet Error_Audit
A1: Legacy and Data Error Audit
A2: Each legacy treatment and identified detail exception is separately logged with correction, quantified impact, basis, and source.
A4: Category | B4: Issue | C4: Legacy / observed treatment | D4: Correct treatment | E4: Quantified impact | F4: Unit | G4: Basis | H4: Source
A5: Legacy model | B5: Management EBITDA did not reverse SBC | C5: Retained -69.275 | D5: Deduct recurring SBC addback | E5: 49.086 | F5: USD mm EBITDA overstatement | G5: CP-03 | H5: /app/input_files/legacy/Candidate_Model_v0.xlsx
A6: Legacy model | B6: Used 2023A valuation denominator | C6: Applied multiple to historical revenue | D6: Use 2024E revenue | E6: 4.8462759 | F6: USD/share understatement at midpoint | G6: CP-05/06 | H6: /app/input_files/legacy/Candidate_Model_v0.xlsx
A7: Legacy model | B7: Applied 0% discount | C7: No execution discount | D7: Apply v3 discount to equity/share | E7: 4.8943917 | F7: USD/share overstatement | G7: CP-09 | H7: /app/input_files/legacy/legacy_assumptions_export.csv
A8: Legacy model | B8: Omitted marketable securities | C8: Cash-only bridge | D8: Add cash and marketable securities | E8: 4.9434299 | F8: USD/share understatement | G8: CP-08 | H8: /app/input_files/legacy/Candidate_Model_v0.xlsx
A9: Legacy model | B9: Treated all 22m Base shares as primary | C9: Primary included secondary | D9: Only SEC primary forms company gross | E9: 228.59808 | F9: USD mm gross overstatement | G9: CP-10 | H9: /app/input_files/legacy/Candidate_Model_v0.xlsx
A10: Legacy model | B10: Included greenshoe in Base | C10: Assumed full exercise | D10: Base excludes option | E10: 106.59 | F10: USD mm net proceeds improperly in Base | G10: CP-11/12 | H10: /app/input_files/legacy/Candidate_Model_v0.xlsx
A11: Legacy model | B11: Fee on all offered shares | C11: Company fee included secondary | D11: Fee only on company primary gross | E11: 11.429904 | F11: USD mm company fee overstatement | G11: CP-12 | H11: /app/input_files/legacy/Candidate_Model_v0.xlsx
A12: Legacy model | B12: Secondary increased share count | C12: Added sold secondary shares | D12: Secondary is transfer | E12: 6.723473 | F12: mm shares overstatement | G12: CP-10 | H12: /app/input_files/legacy/Candidate_Model_v0.xlsx
A13: Legacy model | B13: Secondary proceeds paid to company | C13: Added seller proceeds to company | D13: Company receives zero | E13: 228.59808 | F13: USD mm gross overstatement | G13: CP-10 / SEC-12 | H13: /app/input_files/legacy/Candidate_Model_v0.xlsx
A14: Legacy model | B14: Dilution numerator/denominator mismatch | C14: Post-money equity / pre-money shares | D14: Match equity and share bases; present issuance ratios | F14: Conceptual hard error | G14: CP-10; denominator consistency | H14: /app/input_files/legacy/Candidate_Model_v0.xlsx
A15: Legacy model | B15: High case pushed above $34 | C15: Recommendation anchored to high case | D15: Apply CP-14 tests around midpoint | E15: 3.246831 | F15: USD/share high case above working price | G15: CP-14/15 | H15: /app/input_files/legacy/Candidate_Model_v0.xlsx
A16: Legacy model | B16: Used superseded v2 policy | C16: SBC/10% discount/all-share fee | D16: Use current v3 CP-01–CP-15 | F16: Version control | G16: v2 Revision_Note | H16: /app/input_files/committee/Committee_Policy_v2_20240305.xlsx
A17: Legacy model | B17: Three groups of broken REF links | C17: Valuation, QoE and offering linkage failed | D17: Rebuild formulas from Inputs | E17: 3 | F17: broken formula groups | G17: Candidate model readme | H17: /app/input_files/legacy/Candidate_Model_v0.xlsx
A18: Data anomaly | B18: FY2022 August duplicated at rows 9/14 | C18: Raw sum 723.801 | D18: Exclude row 14 | E18: 57.1 | F18: USD mm overstatement | G18: Tie to SEC-01 | H18: /app/input_files/financials/monthly_revenue_2022_2023.csv
A19: Data anomaly | B19: FY2023 all rows include duplicate-source December | C19: All rows 870.529 | D19: Exclude INT preliminary; retain SEC December | E19: 66.5 | F19: USD mm raw overstatement | G19: CP-02 source priority | H19: /app/input_files/financials/monthly_revenue_2022_2023.csv
A20: Data anomaly | B20: FY2023 INT replaces SEC December scenario | C20: SEC-only adopted 804.029 | D20: INT replacement scenario 801.550 | E20: -2.479 | F20: USD mm replacement scenario difference | G20: Rejected alternative; CP-02 | H20: /app/input_files/financials/monthly_revenue_2022_2023.csv
A21: Data anomaly | B21: FY2023 segment Other decimal typo | C21: Other 152.470; raw 941.252 | D21: Other 15.247; corrected 804.029 | E21: 137.223 | F21: USD mm raw overstatement | G21: SEC-01 annual/segment fact | H21: /app/input_files/financials/revenue_by_segment_2022_2023.csv
A22: Data anomaly | B22: FY2023 SBC TOTAL differs from components | C22: TOTAL 49.680 | D22: Components/SEC 49.086 | E22: 0.594 | F22: USD mm total overstatement | G22: CP-02 | H22: /app/input_files/financials/sbc_detail_2022_2023.csv
A23: Data anomaly | B23: SEC-16 registered count cannot be rebuilt | C23: Reported 141.2; note says exclude RSUs | D23: Annotation implies 138.0; economic 143.716563 | E23: 3.2 | F23: mm shares vs annotation | G23: Use economic count; disclose | H23: /app/input_files/sec_filings/SEC-16_share_count_history.csv
A24: Data anomaly | B24: Cap table Source_ID/as-of conflict | C24: SEC-09-tagged rows dated 2024-03-18 | D24: SEC-09 file is 2024-03-11; retain committee snapshot with flag | F24: Metadata exception | G24: Lineage conflict | H24: /app/input_files/committee/cap_table_snapshot_20240318.csv; /app/input_files/sec_filings/SEC-09_capitalization.csv
A25: Data anomaly | B25: UW-01 absent from master Source_Index | C25: UW-01 used in terms/cap table | D25: Trace directly and flag missing index entry | E25: 1 | F25: missing source ID | G25: Source governance | H25: /app/input_files/sec_filings/Source_Index.csv
A26: Data anomaly | B26: Source_Index misses actual files/IDs | C26: SEC-06, SEC-07, SEC-08, SEC-11, SEC-12, SEC-13, SEC-14, SEC-15, SEC-16 | D26: Use actual files but flag incomplete index | E26: 9 | F26: missing SEC IDs | G26: Source governance | H26: /app/input_files/sec_filings/Source_Index.csv

Sheet Source_Trace
A1: Source Trace
A2: SEC public facts are distinguished from internal committee assumptions; competing values are explicitly disposed.
A4: Item | B4: Adopted value | C4: Unit | D4: Fact type | E4: Adopted source | F4: Competing value | G4: Competing source | H4: Disposition | I4: Reason / policy | J4: Index status
A5: Policy status | B5: v3 current; CP-01–CP-15 | C5: text | D5: Internal committee policy | E5: /app/input_files/committee/Committee_Policy_v3_20240320.xlsx::Committee_Policy!A2:D16 | F5: v2 superseded | G5: /app/input_files/committee/Committee_Policy_v2_20240305.xlsx::Revision_Note!A2:B5 | H5: Adopt v3 | I5: Revision note and committee email; CP-01 | J5: Traced
A6: 2023A revenue | B6: 804.029 | C6: USD mm | D6: SEC public fact | E6: /app/input_files/sec_filings/SEC-01_financials_extract.xlsx::'Public_Financials'!C2 | F6: IR flash 806.200 | G6: /app/input_files/internal/management_flash_20240319.csv | H6: Exclude flash | I6: SEC priority 1 vs INT-01 priority 9; CP-02 | J6: Traced
A7: 2024E growth | B7: 22.0% | C7: % | D7: Internal committee assumption | E7: /app/input_files/committee/Underwriting_Assumptions_20240320.xlsx::'Assumptions'!B2 | F7: Industry 18% | G7: /app/input_files/research/sector_benchmark.md | H7: Retain committee forecast | I7: CP-06 | J7: Traced
A8: 2024E revenue | B8: 980.91538 | C8: USD mm | D8: Calculated internal forecast | E8: /app/input_files/sec_filings/SEC-01_financials_extract.xlsx revenue × /app/input_files/committee/Underwriting_Assumptions_20240320.xlsx growth | F8: None | G8: — | H8: Adopt | I8: CP-06 | J8: Traced
A9: Management Adjusted EBITDA | B9: -69.275 | C9: USD mm | D9: SEC disclosed management non-GAAP | E9: /app/input_files/sec_filings/SEC-01_financials_extract.xlsx::'Public_Financials'!C6 | F9: IR flash -66.100 | G9: /app/input_files/internal/management_flash_20240319.csv | H9: Exclude flash | I9: CP-02/CP-03 | J9: Traced
A10: SBC reversal | B10: 49.086 | C10: USD mm | D10: SEC public fact / underwriting adjustment | E10: /app/input_files/sec_filings/SEC-01_financials_extract.xlsx::'Public_Financials'!C7 | F10: Detail TOTAL 49.680 | G10: /app/input_files/financials/sbc_detail_2022_2023.csv | H10: Use components/SEC amount; flag total | I10: CP-02/CP-03 | J10: Traced
A11: Restructuring | B11: 8.098; incremental 0 | C11: USD mm | D11: SEC public fact / policy treatment | E11: /app/input_files/sec_filings/SEC-01_financials_extract.xlsx::'Public_Financials'!C8; /app/input_files/committee/Committee_Policy_v3_20240320.xlsx::'Committee_Policy'!C5 | F11: Second addback | G11: Potential legacy treatment | H11: No double count | I11: CP-04 | J11: Traced
A12: Underwriting EBITDA | B12: -118.361 | C12: USD mm | D12: Calculated underwriting conclusion | E12: FIN3-WKN-152_qoe_bridge.csv | F12: Management -69.275 | G12: /app/input_files/sec_filings/SEC-01_financials_extract.xlsx | H12: Reverse SBC addback | I12: CP-03 | J12: Traced
A13: Free Cash Flow | B13: -84.838 | C13: USD mm | D13: SEC public fact | E13: /app/input_files/sec_filings/SEC-01_financials_extract.xlsx::'Public_Financials'!C10 | F13: IR flash -82.400 | G13: /app/input_files/internal/management_flash_20240319.csv | H13: Exclude flash | I13: CP-02/CP-13 | J13: Traced
A14: Cash | B14: 401.176 | C14: USD mm | D14: SEC public fact | E14: /app/input_files/sec_filings/SEC-01_financials_extract.xlsx::'Public_Financials'!C11 | F14: — | G14: — | H14: Include | I14: CP-08 | J14: Traced
A15: Marketable securities | B15: 811.946 | C15: USD mm | D15: SEC public fact | E15: /app/input_files/sec_filings/SEC-01_financials_extract.xlsx::'Public_Financials'!C12 | F15: Legacy omitted | G15: /app/input_files/legacy/Candidate_Model_v0.xlsx | H15: Include | I15: CP-08 | J15: Traced
... A28: Source index coverage | B28: Use actual files with explicit trace | C28: text | D28: Source governance anomaly | E28: /app/input_files/sec_filings/Source_Index.csv | F28: SEC-06, SEC-07, SEC-08, SEC-11, SEC-12, SEC-13, SEC-14, SEC-15, SEC-16, UW-01 | G28: Actual file names / UW-01 references | H28: Flag missing IDs | I28: Index incomplete; no inference of priority | J28: Missing/flag

Sheet Tieout_Detail
A1: Detailed Tie-outs
A2: C/D contain recalculable Excel formulas assembled from source detail or linked authority; E is always C minus D.
A4: Area | B4: Displayed calculation / detail | C4: Computed total | D4: Target | E4: Difference | F4: Unit | G4: Exception type | H4: Disposition | I4: Source
A5: Monthly revenue | B5: FY2022 rows 2–14, including duplicate Aug row 14 | C5: =SUM(50.1,50.8,52.3,53.6,54.9,55.7,56.4,57.1,57.9,58.6,59.3,60.001,57.1) -> 723.801 | D5: =Inputs!$B$5 -> 666.701 | E5: =C5-D5 -> 57.1 | F5: USD mm | G5: Duplicate | H5: Exclude row 14 duplicate of row 9 | I5: /app/input_files/financials/monthly_revenue_2022_2023.csv
A6: Monthly revenue | B6: FY2022 rows 2–13; row 14 excluded | C6: =SUM(50.1,50.8,52.3,53.6,54.9,55.7,56.4,57.1,57.9,58.6,59.3,60.001) -> 666.701 | D6: =Inputs!$B$5 -> 666.701 | E6: =C6-D6 -> 0 | F6: USD mm | G6: Resolved | H6: Adopt | I6: /app/input_files/financials/monthly_revenue_2022_2023.csv
A7: Monthly revenue | B7: FY2023 rows 15–27, both Dec sources | C7: =SUM(60.1,61.25,63.4,64.8,66.1,67.3,68.5,69.2,70.1,71.4,72.9,68.979,66.5) -> 870.529 | D7: =Inputs!$B$6 -> 804.029 | E7: =C7-D7 -> 66.5 | F7: USD mm | G7: Competing source row | H7: Exclude INT-01 December | I7: /app/input_files/financials/monthly_revenue_2022_2023.csv
A8: Monthly revenue | B8: FY2023 SEC-01 rows 15–26 | C8: =SUM(60.1,61.25,63.4,64.8,66.1,67.3,68.5,69.2,70.1,71.4,72.9,68.979) -> 804.029 | D8: =Inputs!$B$6 -> 804.029 | E8: =C8-D8 -> 0 | F8: USD mm | G8: Resolved | H8: Adopt | I8: /app/input_files/financials/monthly_revenue_2022_2023.csv
A9: Monthly revenue | B9: Rows 15–25 plus INT-01 Dec row 27 | C9: =SUM(60.1,61.25,63.4,64.8,66.1,67.3,68.5,69.2,70.1,71.4,72.9,66.5) -> 801.55 | D9: =Inputs!$B$6 -> 804.029 | E9: =C9-D9 -> -2.479 | F9: USD mm | G9: Rejected alternative | H9: Exclude; preliminary | I9: /app/input_files/financials/monthly_revenue_2022_2023.csv
A10: Quarterly revenue | B10: Rows 2–5: Q1+Q2+Q3+Q4 | C10: =SUM(184.75,198.2,207.8,213.279) -> 804.029 | D10: =Inputs!$B$6 -> 804.029 | E10: =C10-D10 -> 0 | F10: USD mm | G10: None | H10: Adopt as corroboration | I10: /app/input_files/financials/revenue_quarterly.csv
A11: Segment revenue | B11: Rows 4–5: Advertising + raw Other | C11: =SUM(788.782,152.47) -> 941.252 | D11: =Inputs!$B$6 -> 804.029 | E11: =C11-D11 -> 137.223 | F11: USD mm | G11: Decimal typo | H11: Replace Other from SEC-01 | I11: /app/input_files/financials/revenue_by_segment_2022_2023.csv
A12: Segment revenue | B12: Advertising row 4 + SEC-01 Other (15.247) | C12: =SUM(788.782,15.247) -> 804.029 | D12: =Inputs!$B$6 -> 804.029 | E12: =C12-D12 -> 0 | F12: USD mm | G12: Resolved | H12: Adopt | I12: /app/input_files/financials/revenue_by_segment_2022_2023.csv; /app/input_files/sec_filings/SEC-01_financials_extract.xlsx
A13: Geographic revenue | B13: FY2023 rows 4–5: US + International | C13: =SUM(620.5,183.529) -> 804.029 | D13: =Inputs!$B$6 -> 804.029 | E13: =C13-D13 -> 0 | F13: USD mm | G13: None | H13: Adopt as corroboration | I13: /app/input_files/sec_filings/SEC-05_revenue_by_geo.csv
A14: SBC | B14: FY2023 component rows 6–9 | C14: =SUM(38.5,5.2,1.9,3.486) -> 49.086 | D14: =Inputs!$B$9 -> 49.086 | E14: =C14-D14 -> 0 | F14: USD mm | G14: None | H14: Adopt components | I14: /app/input_files/financials/sbc_detail_2022_2023.csv
A15: SBC | B15: FY2023 reported TOTAL row 10 | C15: =SUM(49.68,0) -> 49.68 | D15: =Inputs!$B$9 -> 49.086 | E15: =C15-D15 -> 0.594 | F15: USD mm | G15: Total mismatch | H15: Reject TOTAL row | I15: /app/input_files/financials/sbc_detail_2022_2023.csv
A16: Restructuring | B16: Component rows 2–4 | C16: =SUM(5.998,1.4,0.7) -> 8.098 | D16: =Inputs!$B$10 -> 8.098 | E16: =C16-D16 -> 0 | F16: USD mm | G16: None | H16: Already adjusted; incremental zero | I16: /app/input_files/financials/restructuring_detail_2023.csv
A17: Restructuring | B17: Reported TOTAL row 5 | C17: =SUM(8.098,0) -> 8.098 | D17: =Inputs!$B$10 -> 8.098 | E17: =C17-D17 -> 0 | F17: USD mm | G17: None | H17: No second addback | I17: /app/input_files/financials/restructuring_detail_2023.csv
A18: FCF | B18: Rows 2–3: operating cash flow − absolute capex | C18: =-52.026-ABS(-32.812) -> -84.838 | D18: =Inputs!$B$11 -> -84.838 | E18: =C18-D18 -> 0 | F18: USD mm | G18: None | H18: Adopt | I18: /app/input_files/financials/fcf_bridge_2023.csv
A19: CFS | B19: Rows 2–4: operating + investing + financing | C19: =SUM(-52.026,-45.1,62.492) -> -34.634 | D19: =SUM(-34.634,0) -> -34.634 | E19: =C19-D19 -> 0 | F19: USD mm | G19: None | H19: Ties to net change | I19: /app/input_files/financials/cash_flow_statement_2023.csv
A20: CFS | B20: Rows 5–6: beginning cash + net change | C20: =SUM(435.81,-34.634) -> 401.176 | D20: =SUM(401.176,0) -> 401.176 | E20: =C20-D20 -> 0 | F20: USD mm | G20: None | H20: Ties to ending cash | I20: /app/input_files/financials/cash_flow_statement_2023.csv
A21: Balance sheet | B21: Rows 2–3: cash + marketable securities | C21: =SUM(401.176,811.946) -> 1213.122 | D21: =SUM(1213.122,0) -> 1213.122 | E21: =C21-D21 -> 0 | F21: USD mm | G21: None | H21: Both included in equity bridge | I21: /app/input_files/financials/balance_sheet_summary_2022_2023.csv
A22: Income statement | B22: Revenue row 2 | C22: =SUM(804.029,0) -> 804.029 | D22: =Inputs!$B$6 -> 804.029 | E22: =C22-D22 -> 0 | F22: USD mm | G22: None | H22: Adopt | I22: /app/input_files/financials/income_statement_2022_2023.csv
A23: Income statement | B23: Net income (loss) row 9 vs deficit movement | C23: =SUM(-90.824,0) -> -90.824 | D23: =SUM(-1299.224,-(-1208.4)) -> -90.824 | E23: =C23-D23 -> 0 | F23: USD mm | G23: None | H23: Adopt | I23: /app/input_files/financials/income_statement_2022_2023.csv
A24: Operating expenses | B24: Rows 2–5: cost of revenue + R&D + S&M + G&A | C24: =SUM(119.9,438.4,196.3,158.9) -> 913.5 | D24: =SUM(913.5,0) -> 913.5 | E24: =C24-D24 -> 0 | F24: USD mm | G24: None | H24: Ties | I24: /app/input_files/financials/opex_summary_2022_2023.csv
A25: Accumulated deficit | B25: FY2023 less FY2022, equity row 3 | C25: =-1299.224-(-1208.4) -> -90.824 | D25: =SUM(-90.824,0) -> -90.824 | E25: =C25-D25 -> 0 | F25: USD mm | G25: None | H25: Ties to net loss | I25: /app/input_files/financials/stockholders_equity_summary.csv
A26: Cap table | B26: Rows 2–7 committee components | C26: =SUM(40,70,15,10,5.716563,3) -> 143.71656 | D26: =Inputs!$B$14 -> 143.71656 | E26: =C26-D26 -> 0 | F26: mm shares | G26: None | H26: Arithmetic holds | I26: /app/input_files/committee/cap_table_snapshot_20240318.csv
A27: Cap table | B27: SEC-09 rows 2–7 components | C27: =SUM(40,70,15,10,5.716563,3) -> 143.71656 | D27: =Inputs!$B$14 -> 143.71656 | E27: =C27-D27 -> 0 | F27: mm shares | G27: Metadata mismatch | H27: Value supports economic count; as-of differs | I27: /app/input_files/sec_filings/SEC-09_capitalization.csv
A28: Cap table | B28: SEC-16 row 5 registered vs economic | C28: =SUM(141.2,0) -> 141.2 | D28: =Inputs!$B$14 -> 143.71656 | E28: =C28-D28 -> -2.516563 | F28: mm shares | G28: Unreconciled | H28: Do not use registered count | I28: /app/input_files/sec_filings/SEC-16_share_count_history.csv
A29: Cap table | B29: Committee components excluding unsettled RSUs vs SEC-16 row 5 | C29: =SUM(40,70,15,10,3) -> 138 | D29: =SUM(141.2,0) -> 141.2 | E29: =C29-D29 -> -3.2 | F29: mm shares | G29: Unreconciled annotation | H29: Flag 3.2m gap | I29: /app/input_files/sec_filings/SEC-16_share_count_history.csv
A30: Offering shares | B30: Committee Base primary + secondary | C30: =SUM(Inputs!$B$20,Inputs!$B$22) -> 22 | D30: =SUM(Inputs!$B$25,Inputs!$B$26) -> 22 | E30: =C30-D30 -> 0 | F30: mm shares | G30: None | H30: Base sold shares; secondary not new | I30: /app/input_files/sec_filings/SEC-03_offering_terms.xlsx
A31: Offering shares | B31: Committee Base primary + secondary + shoe | C31: =SUM(Inputs!$B$20,Inputs!$B$22,Inputs!$B$24) -> 25.3 | D31: =SUM(Inputs!$B$25,Inputs!$B$26,Inputs!$B$27) -> 25.3 | E31: =C31-D31 -> 0 | F31: mm shares | G31: None | H31: Full option scenario | I31: /app/input_files/sec_filings/SEC-03_offering_terms.xlsx

Sheet Methodology
A1: Methodology and Reproduction Checks
A2: Control hierarchy, valuation rationale, named structural checks, governance exceptions, and file inventory.
A4: Section | B4: Item | C4: Result | D4: Status | E4: Basis
A5: Method | B5: Information cutoff | C5: 2024-03-20 pre-pricing only | D5: PASS | E5: CP-01
A6: Method | B6: Source hierarchy | C6: Source_Index priority; v3 resolves equal-priority policy | D6: PASS | E6: CP-02 and README
A7: Method | B7: Profitability | C7: Reverse SBC; no repeat restructuring addback | D7: PASS | E7: CP-03/04
A8: Method | B8: Primary valuation | C8: EV / 2024E Revenue because underwriting EBITDA remains negative | D8: PASS | E8: CP-05
A9: Method | B9: Equity bridge | C9: EV + cash + marketable securities | D9: PASS | E9: CP-08
A10: Method | B10: Discount placement | C10: After equity value per share | D10: PASS | E10: CP-09
A11: Method | B11: Offering mechanics | C11: Secondary excluded from proceeds/new shares; shoe separate | D11: PASS | E11: CP-10/11/12
A12: Boundary | B12: SEC-02 | C12: 32.50 − 11.17 = 21.33; no extrapolation | D12: PASS | E12: Cross-check only
A13: Structure check | B13: committee/SEC primary-secondary-shoe agreement | C13: =AND(Inputs!$B$20=Inputs!$B$25,Inputs!$B$22=Inputs!$B$26,Inputs!$B$24=Inputs!$B$27) -> TRUE | D13: PASS | E13: Included in Pricing_Summary Test 3
A14: Structure check | B14: full primary equals base primary plus shoe | C14: =Inputs!$B$21=Inputs!$B$20+Inputs!$B$24 -> TRUE | D14: PASS | E14: Included in Pricing_Summary Test 3
A15: Structure check | B15: base sold equals primary plus secondary | C15: =Offering_Proceeds!B9=Inputs!$B$25+Inputs!$B$26 -> TRUE | D15: PASS | E15: Included in Pricing_Summary Test 3
A16: Structure check | B16: Base shoe model treatment equals zero | C16: =AND(Inputs!$B$23=0,Offering_Proceeds!B8=0) -> TRUE | D16: PASS | E16: Included in Pricing_Summary Test 3
A17: Structure check | B17: secondary company proceeds model treatment equals zero | C17: =Offering_Proceeds!B15=0 -> TRUE | D17: PASS | E17: Included in Pricing_Summary Test 3
A18: Structure check | B18: Base share-capital bridge | C18: =Dilution!B8=Inputs!$B$14+Inputs!$B$20 -> TRUE | D18: PASS | E18: Included in Pricing_Summary Test 3
A19: Structure check | B19: Full share-capital bridge | C19: =Dilution!C8=Inputs!$B$14+Inputs!$B$20+Inputs!$B$24 -> TRUE | D19: PASS | E19: Included in Pricing_Summary Test 3
A20: Structure check | B20: underwriting fee applies only to primary gross | C20: =AND(Offering_Proceeds!B12=Offering_Proceeds!B10*Offering_Proceeds!B11,Offering_Proceeds!C12=Offering_Proceeds!C10*Offering_Proceeds!C11) -> TRUE | D20: PASS | E20: Included in Pricing_Summary Test 3
A21: Structure check | B21: fixed company expense deducted once per scenario | C21: =AND(Offering_Proceeds!B14=Offering_Proceeds!B10-Offering_Proceeds!B12-Offering_Proceeds!B13,Offering_Proceeds!C14=Offering_Proceeds!C10-Offering_Proceeds!C12-Offering_Proceeds!C13) -> TRUE | D21: PASS | E21: Included in Pricing_Summary Test 3
A22: Structure check | B22: core normal/corrected tie-outs pass | C22: =AND(ABS(Tieout_Detail!E6)<0.0000001,ABS(Tieout_Detail!E8)<0.0000001,ABS(Tieout_Detail!E10)<0.0000001,ABS(Tieout_Detail!E12)<0.0000001,ABS(Tieout_Detail!E13)<0.0000001,ABS(Tieout_Detail!E14)<0.0000001,ABS(Tieout_Detail!E16)<0.0000001,ABS(Tieout_Detail!E17)<0.0000001,ABS(Tieout_Detail!E18)<0.0000001,ABS(Tieout_Detail!E21)<0.0000001,ABS(Tieout_Detail!E22)<0.0000001,ABS(Tieout_Detail!E25)<0.0000001,ABS(Tieout_Detail!E26)<0.0000001,ABS(Tieout_Detail!E30)<0.0000001,ABS(Tieout_Detail!E31)<0.0000001) -> TRUE | D22: PASS | E22: Included in Pricing_Summary Test 3
A23: Inventory | B23: committee | C23: 8 | D23: COUNT | E23: Input files
A24: Inventory | B24: sec_filings | C24: 17 | D24: COUNT | E24: Input files
A25: Inventory | B25: financials | C25: 14 | D25: COUNT | E25: Input files
A26: Inventory | B26: comps | C26: 4 | D26: COUNT | E26: Input files
A27: Inventory | B27: research | C27: 5 | D27: COUNT | E27: Input files
A28: Inventory | B28: internal | C28: 6 | D28: COUNT | E28: Input files
A29: Inventory | B29: legacy | C29: 4 | D29: COUNT | E29: Input files
A30: Inventory | B30: Seven source directories subtotal | C30: 58 | D30: COUNT | E30: Derived by pathlib
A31: Inventory | B31: Root files | C31: 2 | D31: COUNT | E31: README + data dictionary
A32: Inventory | B32: Total source files | C32: 60 | D32: COUNT | E32: Seven directories + root
A33: Check | B33: QoE bridge | C33: -69.275 − 49.086 = -118.361 | D33: PASS | E33: CP-03
A34: Check | B34: Base proceeds | C34: Gross 519.401918; fee 25.9700959; net 486.4318221 | D34: PASS | E34: CP-12
A35: Check | B35: Full proceeds | C35: Gross 631.601918; fee 31.5800959; net 593.0218221 | D35: PASS | E35: CP-12
A36: Check | B36: Pricing decision | C36: Proceed | D36: PASS | E36: CP-14/15; all three Pricing_Summary tests
A37: Governance exception | B37: SEC-16 registered/economic count | C37: Registered 141.200000; economic 143.716563; unresolved | D37: FLAG | E37: Disclosed exception, excluded from structural hard-error gate
A38: Governance exception | B38: Missing actual source IDs | C38: SEC-06, SEC-07, SEC-08, SEC-11, SEC-12, SEC-13, SEC-14, SEC-15, SEC-16, UW-01 | D38: FLAG | E38: Source_Index incomplete; excluded from structural hard-error gate
