Workbook

Sheet Inputs
A1: Input / control item | B1: Value | C1: Unit | D1: Source / formula | E1: Classification | F1: Notes
A2: Information cut-off | B2: 2024-03-20 | C2: date | D2: 00_README.md; CP-01 | E2: Control | F2: Formal pricing pre-cutoff
A3: Controlling policy version | B3: v3 | C3: version | D3: committee/Committee_Policy_v3_20240320.xlsx | E3: Internal committee policy | F3: v2 superseded
A4: 2022 Revenue | B4: 666.701 | C4: USD mm | D4: SEC-01 | E4: SEC public fact | F4: Audited historical
A5: 2023 Revenue | B5: 804.029 | C5: USD mm | D5: SEC-01 | E5: SEC public fact | F5: Audited historical
A6: 2022 Net income (loss) | B6: -158.55 | C6: USD mm | D6: SEC-01 | E6: SEC public fact | F6: Audited historical
A7: 2023 Net income (loss) | B7: -90.824 | C7: USD mm | D7: SEC-01 | E7: SEC public fact | F7: Audited historical
A8: 2022 Management Adjusted EBITDA | B8: -108.393 | C8: USD mm | D8: SEC-01 | E8: SEC public non-GAAP fact | F8: Outside auditor opinion
A9: 2023 Management Adjusted EBITDA | B9: -69.275 | C9: USD mm | D9: SEC-01 | E9: SEC public non-GAAP fact | F9: Outside auditor opinion
A10: 2022 SBC & related taxes | B10: 55.768 | C10: USD mm | D10: SEC-01 | E10: SEC public fact | F10: Detail tie-out complete
A11: 2023 SBC & related taxes | B11: 49.086 | C11: USD mm | D11: SEC-01 | E11: SEC public fact | F11: Detail tie-out complete
A12: 2022 Restructuring | B12: 0 | C12: USD mm | D12: SEC-01 | E12: SEC public fact
A13: 2023 Restructuring | B13: 8.098 | C13: USD mm | D13: SEC-01 | E13: SEC public fact | F13: Already adjusted in management EBITDA
A14: 2022 Free Cash Flow | B14: -100.254 | C14: USD mm | D14: SEC-01 | E14: SEC public non-GAAP fact
A15: 2023 Free Cash Flow | B15: -84.838 | C15: USD mm | D15: SEC-01 | E15: SEC public non-GAAP fact | F15: OCF less capex ties
A16: 2022 Cash | B16: 435.81 | C16: USD mm | D16: SEC-01 | E16: SEC public fact
A17: 2023 Cash | B17: 401.176 | C17: USD mm | D17: SEC-01 | E17: SEC public fact
A18: 2022 Marketable securities | B18: 830.734 | C18: USD mm | D18: SEC-01 | E18: SEC public fact
A19: 2023 Marketable securities | B19: 811.946 | C19: USD mm | D19: SEC-01 | E19: SEC public fact | F19: Must enter net cash bridge
A20: SEC preliminary NTBV/share | B20: 11.17 | C20: USD/share | D20: SEC-02 | E20: SEC public fact | F20: Only at assumed $32.50
A21: SEC assumed price for dilution | B21: 32.5 | C21: USD/share | D21: SEC-02 | E21: SEC public fact | F21: Cross-check only
A22: SEC preliminary immediate dilution | B22: 21.33 | C22: USD/share | D22: SEC-02 | E22: SEC public fact | F22: Cross-check only
A23: 2024E revenue growth | B23: 0.22 | C23: % | D23: committee/Underwriting_Assumptions_20240320.xlsx; CP-06 | E23: Internal committee assumption | F23: Not an SEC fact
A24: Peer low | B24: 4 | C24: x | D24: committee/Underwriting_Assumptions_20240320.xlsx; CP-07 | E24: Internal committee assumption | F24: Bank comps are cross-check only
A25: Peer midpoint | B25: 4.5 | C25: x | D25: committee/Underwriting_Assumptions_20240320.xlsx; CP-07 | E25: Internal committee assumption
A26: Peer high | B26: 5 | C26: x | D26: committee/Underwriting_Assumptions_20240320.xlsx; CP-07 | E26: Internal committee assumption
A27: IPO execution discount | B27: 0.125 | C27: % | D27: committee/Underwriting_Assumptions_20240320.xlsx; CP-09 | E27: Internal committee assumption | F27: Apply to equity value/share
A28: Proposed committee price | B28: 34 | C28: USD/share | D28: committee/Offering_Terms_20240320.xlsx | E28: Internal committee assumption | F28: Decision input, not actual result
A29: Base primary shares | B29: 15.276527 | C29: mm shares | D29: SEC-03 | E29: SEC public fact | F29: New company shares
A30: Base secondary shares | B30: 6.723473 | C30: mm shares | D30: SEC-03 | E30: SEC public fact | F30: No company proceeds or share increase
A31: Greenshoe shares | B31: 3.3 | C31: mm shares | D31: SEC-03 | E31: SEC public fact | F31: Excluded from Base
A32: Pre-money economic shares | B32: 143.71656 | C32: mm shares | D32: committee cap-table snapshot / SEC-09 components | E32: Internal committee assumption | F32: Includes vested unsettled RSUs and in-money options
A33: Underwriting fee rate | B33: 0.05 | C33: % | D33: committee/Offering_Terms_20240320.xlsx; SEC-10 basis | E33: Internal committee assumption | F33: Primary gross only
A34: Fixed company expenses | B34: 7 | C34: USD mm | D34: committee/Offering_Terms_20240320.xlsx | E34: Internal committee assumption | F34: Do not repeat on greenshoe increment
A35: Preliminary filing range low | B35: 31 | C35: USD/share | D35: SEC-03 | E35: SEC public fact | F35: Execution cross-check only
A36: Preliminary filing range high | B36: 34 | C36: USD/share | D36: SEC-03 | E36: SEC public fact | F36: Execution cross-check only

Sheet QoE
A1: Metric / check | B1: 2022A | C1: 2023A | D1: Unit | E1: Formula / conclusion | F1: Source / policy
A2: Revenue | B2: =Inputs!B4 -> 666.701 | C2: =Inputs!B5 -> 804.029 | D2: USD mm | E2: SEC reported | F2: SEC-01
A3: Revenue growth | C3: =C2/B2-1 -> 0.20598139 | D3: % | E3: 2023A / 2022A - 1 | F3: Calculated
A4: Net income (loss) | B4: =Inputs!B6 -> -158.55 | C4: =Inputs!B7 -> -90.824 | D4: USD mm | E4: SEC reported | F4: SEC-01
A5: Management Adjusted EBITDA | B5: =Inputs!B8 -> -108.393 | C5: =Inputs!B9 -> -69.275 | D5: USD mm | E5: Starting point; non-GAAP | F5: SEC-01 / CP-03
A6: Less: SBC & related taxes | B6: =-Inputs!B10 -> -55.768 | C6: =-Inputs!B11 -> -49.086 | D6: USD mm | E6: Reverse management addback | F6: CP-03
A7: Restructuring incremental adjustment | B7: 0 | C7: 0 | D7: USD mm | E7: No second adjustment | F7: CP-04
A8: Underwriting EBITDA | B8: =B5+B6+B7 -> -164.161 | C8: =C5+C6+C7 -> -118.361 | D8: USD mm | E8: Remains negative | F8: CP-03/CP-04
A9: Free Cash Flow | B9: =Inputs!B14 -> -100.254 | C9: =Inputs!B15 -> -84.838 | D9: USD mm | E9: Remains negative | F9: SEC-01 / CP-13
A10: Cash & cash equivalents | B10: =Inputs!B16 -> 435.81 | C10: =Inputs!B17 -> 401.176 | D10: USD mm | F10: SEC-01
A11: Marketable securities | B11: =Inputs!B18 -> 830.734 | C11: =Inputs!B19 -> 811.946 | D11: USD mm | F11: SEC-01
A12: Cash + marketable securities | B12: =B10+B11 -> 1266.544 | C12: =C10+C11 -> 1213.122 | D12: USD mm | E12: Net cash bridge input | F12: CP-08
A14: Detailed tie-out | B14: Calculated | C14: Reported | D14: Difference | E14: Disposition | F14: Source
A15: Monthly revenue FY2022 | B15: 666.701 | C15: 666.701 | D15: -1.1368684e-13 | E15: Exclude duplicate-export | F15: monthly revenue / SEC-01
A16: Monthly revenue FY2023 | B16: 804.029 | C16: 804.029 | D16: 0 | E16: Exclude preliminary residue | F16: monthly revenue / SEC-01
A17: Quarterly revenue FY2023 | B17: 804.029 | C17: 804.029 | D17: 0 | E17: Ties | F17: quarterly revenue / SEC-01
A18: Segment revenue FY2022 | B18: 666.701 | C18: 666.701 | D18: 0 | E18: Ties | F18: segment revenue / SEC-01
A19: Segment revenue FY2023 | B19: 804.029 | C19: 804.029 | D19: 0 | E19: Ties | F19: segment revenue / SEC-01
A20: Geography revenue FY2022 | B20: 666.701 | C20: 666.701 | D20: 0 | E20: Ties | F20: SEC-05 / SEC-01
A21: Geography revenue FY2023 | B21: 804.029 | C21: 804.029 | D21: 0 | E21: Ties | F21: SEC-05 / SEC-01
A22: SBC detail FY2023 | B22: 49.086 | C22: 49.086 | D22: 0 | E22: Ties | F22: SBC detail / SEC-01
A23: Restructuring detail FY2023 | B23: 8.098 | C23: 8.098 | D23: -1.7763568e-15 | E23: Ties; no double addback | F23: restructuring detail / SEC-01
A24: FCF FY2023 | B24: -84.838 | C24: -84.838 | D24: 0 | E24: OCF + capex outflow | F24: FCF bridge / SEC-01
A25: Cash movement FY2023 | B25: -34.634 | C25: -34.634 | D25: -1.4210855e-14 | E25: Ties | F25: cash flow / SEC-01
A26: Net loss FY2023 | B26: -90.824 | C26: -90.824 | D26: -1.4210855e-14 | E26: Revenue + total opex + other income | F26: income statement / SEC-01

Sheet Valuation
A1: Valuation step | B1: Low | C1: Mid | D1: High | E1: Unit / note
A2: 2024E Revenue | B2: =Inputs!B5*(1+Inputs!B23) -> 980.91538 | C2: =B2 -> 980.91538 | D2: =B2 -> 980.91538 | E2: 2023A × (1 + internal growth assumption)
A3: EV / Revenue multiple | B3: =Inputs!B24 -> 4 | C3: =Inputs!B25 -> 4.5 | D3: =Inputs!B26 -> 5 | E3: Committee CP-07
A4: Enterprise Value | B4: =B2*B3 -> 3923.6615 | C4: =C2*C3 -> 4414.1192 | D4: =D2*D3 -> 4904.5769 | E4: USD mm
A5: Add: Cash | B5: =Inputs!B17 -> 401.176 | C5: =B5 -> 401.176 | D5: =B5 -> 401.176 | E5: USD mm
A6: Add: Marketable securities | B6: =Inputs!B19 -> 811.946 | C6: =B6 -> 811.946 | D6: =B6 -> 811.946 | E6: USD mm
A7: Pre-money Equity Value | B7: =SUM(B4:B6) -> 5136.7835 | C7: =SUM(C4:C6) -> 5627.2412 | D7: =SUM(D4:D6) -> 6117.6989 | E7: USD mm
A8: Pre-money economic shares | B8: =Inputs!B32 -> 143.71656 | C8: =B8 -> 143.71656 | D8: =B8 -> 143.71656 | E8: mm shares
A9: Undiscounted equity value/share | B9: =B7/B8 -> 35.74246 | C9: =C7/C8 -> 39.155133 | D9: =D7/D8 -> 42.567807 | E9: USD/share
A10: Execution discount | B10: =Inputs!B27 -> 0.125 | C10: =B10 -> 0.125 | D10: =B10 -> 0.125 | E10: Internal CP-09
A11: Committee supported price/share | B11: =B9*(1-B10) -> 31.274653 | C11: =C9*(1-C10) -> 34.260742 | D11: =D9*(1-D10) -> 37.246831 | E11: USD/share
A12: Proposed price | B12: =Inputs!B28 -> 34 | C12: =B12 -> 34 | D12: =B12 -> 34 | E12: Internal decision input
A13: Proposed less supported value | B13: =B12-B11 -> 2.7253474 | C13: =C12-C11 -> -0.26074181 | D13: =D12-D11 -> -3.246831 | E13: USD/share

Sheet Sensitivity
A1: 2024E growth × EV/Revenue | B1: 4.00x | C1: 4.25x | D1: 4.50x | E1: 4.75x | F1: 5.00x | G1: Row definition
A2: 0.20598139 | B2: =((Inputs!$B$5*(1+$A2)*4+Inputs!$B$17+Inputs!$B$19)/Inputs!$B$32)*(1-Inputs!$B$27) -> 31.000155 | C2: =((Inputs!$B$5*(1+$A2)*4.25+Inputs!$B$17+Inputs!$B$19)/Inputs!$B$32)*(1-Inputs!$B$27) -> 32.476044 | D2: =((Inputs!$B$5*(1+$A2)*4.5+Inputs!$B$17+Inputs!$B$19)/Inputs!$B$32)*(1-Inputs!$B$27) -> 33.951933 | E2: =((Inputs!$B$5*(1+$A2)*4.75+Inputs!$B$17+Inputs!$B$19)/Inputs!$B$32)*(1-Inputs!$B$27) -> 35.427821 | F2: =((Inputs!$B$5*(1+$A2)*5+Inputs!$B$17+Inputs!$B$19)/Inputs!$B$32)*(1-Inputs!$B$27) -> 36.90371 | G2: 2023A actual growth anchor
A3: 0.2129907 | B3: =((Inputs!$B$5*(1+$A3)*4+Inputs!$B$17+Inputs!$B$19)/Inputs!$B$32)*(1-Inputs!$B$27) -> 31.137404 | C3: =((Inputs!$B$5*(1+$A3)*4.25+Inputs!$B$17+Inputs!$B$19)/Inputs!$B$32)*(1-Inputs!$B$27) -> 32.621871 | D3: =((Inputs!$B$5*(1+$A3)*4.5+Inputs!$B$17+Inputs!$B$19)/Inputs!$B$32)*(1-Inputs!$B$27) -> 34.106337 | E3: =((Inputs!$B$5*(1+$A3)*4.75+Inputs!$B$17+Inputs!$B$19)/Inputs!$B$32)*(1-Inputs!$B$27) -> 35.590804 | F3: =((Inputs!$B$5*(1+$A3)*5+Inputs!$B$17+Inputs!$B$19)/Inputs!$B$32)*(1-Inputs!$B$27) -> 37.07527 | G3: Mechanical step
A4: 0.22 | B4: =((Inputs!$B$5*(1+$A4)*4+Inputs!$B$17+Inputs!$B$19)/Inputs!$B$32)*(1-Inputs!$B$27) -> 31.274653 | C4: =((Inputs!$B$5*(1+$A4)*4.25+Inputs!$B$17+Inputs!$B$19)/Inputs!$B$32)*(1-Inputs!$B$27) -> 32.767697 | D4: =((Inputs!$B$5*(1+$A4)*4.5+Inputs!$B$17+Inputs!$B$19)/Inputs!$B$32)*(1-Inputs!$B$27) -> 34.260742 | E4: =((Inputs!$B$5*(1+$A4)*4.75+Inputs!$B$17+Inputs!$B$19)/Inputs!$B$32)*(1-Inputs!$B$27) -> 35.753786 | F4: =((Inputs!$B$5*(1+$A4)*5+Inputs!$B$17+Inputs!$B$19)/Inputs!$B$32)*(1-Inputs!$B$27) -> 37.246831 | G4: Base growth
A5: 0.2270093 | B5: =((Inputs!$B$5*(1+$A5)*4+Inputs!$B$17+Inputs!$B$19)/Inputs!$B$32)*(1-Inputs!$B$27) -> 31.411901 | C5: =((Inputs!$B$5*(1+$A5)*4.25+Inputs!$B$17+Inputs!$B$19)/Inputs!$B$32)*(1-Inputs!$B$27) -> 32.913524 | D5: =((Inputs!$B$5*(1+$A5)*4.5+Inputs!$B$17+Inputs!$B$19)/Inputs!$B$32)*(1-Inputs!$B$27) -> 34.415146 | E5: =((Inputs!$B$5*(1+$A5)*4.75+Inputs!$B$17+Inputs!$B$19)/Inputs!$B$32)*(1-Inputs!$B$27) -> 35.916769 | F5: =((Inputs!$B$5*(1+$A5)*5+Inputs!$B$17+Inputs!$B$19)/Inputs!$B$32)*(1-Inputs!$B$27) -> 37.418392 | G5: Mechanical step
A6: 0.23401861 | B6: =((Inputs!$B$5*(1+$A6)*4+Inputs!$B$17+Inputs!$B$19)/Inputs!$B$32)*(1-Inputs!$B$27) -> 31.54915 | C6: =((Inputs!$B$5*(1+$A6)*4.25+Inputs!$B$17+Inputs!$B$19)/Inputs!$B$32)*(1-Inputs!$B$27) -> 33.05935 | D6: =((Inputs!$B$5*(1+$A6)*4.5+Inputs!$B$17+Inputs!$B$19)/Inputs!$B$32)*(1-Inputs!$B$27) -> 34.569551 | E6: =((Inputs!$B$5*(1+$A6)*4.75+Inputs!$B$17+Inputs!$B$19)/Inputs!$B$32)*(1-Inputs!$B$27) -> 36.079752 | F6: =((Inputs!$B$5*(1+$A6)*5+Inputs!$B$17+Inputs!$B$19)/Inputs!$B$32)*(1-Inputs!$B$27) -> 37.589952 | G6: Mechanical step
A8: Method note | B8: Growth grid is mechanically derived from 2023A actual growth and the committee base; multiples interpolate the committee range. Non-base cells are sensitivities, not forecasts.

Sheet Offering_Proceeds
A1: Item | B1: Base | C1: Full Exercise | D1: Unit / treatment
A2: Proposed price | B2: =Inputs!B28 -> 34 | C2: =Inputs!B28 -> 34 | D2: USD/share; internal decision input
A3: Primary shares | B3: =Inputs!B29 -> 15.276527 | C3: =Inputs!B29+Inputs!B31 -> 18.576527 | D3: mm shares
A4: Secondary shares | B4: =Inputs!B30 -> 6.723473 | C4: =Inputs!B30 -> 6.723473 | D4: mm shares; no company proceeds
A5: Greenshoe shares | B5: 0 | C5: =Inputs!B31 -> 3.3 | D5: mm shares; Base excludes
A6: Company primary gross proceeds | B6: =B2*B3 -> 519.40192 | C6: =C2*C3 -> 631.60192 | D6: USD mm
A7: Secondary gross proceeds | B7: =B2*B4 -> 228.59808 | C7: =C2*C4 -> 228.59808 | D7: USD mm; to selling holders
A8: Company underwriting fee | B8: =B6*Inputs!B33 -> 25.970096 | C8: =C6*Inputs!B33 -> 31.580096 | D8: USD mm; primary gross only
A9: Fixed company expenses | B9: =Inputs!B34 -> 7 | C9: =Inputs!B34 -> 7 | D9: USD mm; once per total scenario
A10: Company net primary proceeds | B10: =B6-B8-B9 -> 486.43182 | C10: =C6-C8-C9 -> 593.02182 | D10: USD mm
A11: Incremental net proceeds vs Base | B11: 0 | C11: =C10-B10 -> 106.59 | D11: USD mm; no repeat fixed expense

Sheet Dilution
A1: Item | B1: Base | C1: Full Exercise | D1: Unit / note
A2: Pre-money economic shares | B2: =Inputs!B32 -> 143.71656 | C2: =Inputs!B32 -> 143.71656 | D2: mm shares
A3: New primary shares | B3: =Inputs!B29 -> 15.276527 | C3: =Inputs!B29+Inputs!B31 -> 18.576527 | D3: mm shares
A4: Secondary shares (no share increase) | B4: =Inputs!B30 -> 6.723473 | C4: =Inputs!B30 -> 6.723473 | D4: mm shares; transfer only
A5: Post-money economic shares | B5: =B2+B3 -> 158.99309 | C5: =C2+C3 -> 162.29309 | D5: mm shares
A6: New primary / post-money | B6: =B3/B5 -> 0.096082962 | C6: =C3/C5 -> 0.11446283 | D6: %
A7: New primary / pre-money | B7: =B3/B2 -> 0.10629622 | C7: =C3/C2 -> 0.12925808 | D7: %
A8: Secondary impact on company shares | B8: 0 | C8: 0 | D8: mm shares
A9: SEC assumed price | B9: =Inputs!B21 -> 32.5 | C9: =B9 -> 32.5 | D9: USD/share; cross-check only
A10: SEC preliminary NTBV/share | B10: =Inputs!B20 -> 11.17 | C10: =B10 -> 11.17 | D10: USD/share; only at SEC assumed price
A11: SEC preliminary immediate dilution | B11: =Inputs!B22 -> 21.33 | C11: =B11 -> 21.33 | D11: USD/share; only at SEC assumed price
A12: SEC arithmetic cross-check | B12: =B10+B11-B9 -> 0 | C12: =C10+C11-C9 -> 0 | D12: Should be zero

Sheet Pricing_Summary
A1: Decision item | B1: Result | C1: Unit | D1: Cross-reference / interpretation
A2: 2023 Underwriting EBITDA | B2: =QoE!C8 -> -118.361 | C2: USD mm | D2: Negative; EV/EBITDA not used
A3: 2023 Free Cash Flow | B3: =QoE!C9 -> -84.838 | C3: USD mm | D3: Negative QoE risk
A4: 2024E Revenue | B4: =Valuation!C2 -> 980.91538 | C4: USD mm | D4: 2023A × (1 + internal committee growth)
A5: Supported range low | B5: =Valuation!B11 -> 31.274653 | C5: USD/share | D5: Low multiple after execution discount
A6: Supported midpoint | B6: =Valuation!C11 -> 34.260742 | C6: USD/share | D6: Mid multiple after execution discount
A7: Supported range high | B7: =Valuation!D11 -> 37.246831 | C7: USD/share | D7: High multiple after execution discount
A8: Proposed price | B8: =Valuation!C12 -> 34 | C8: USD/share | D8: Internal input; not actual final price
A9: Proposed less midpoint | B9: =B8-B6 -> -0.26074181 | C9: USD/share | D9: Negative means below midpoint
A10: Absolute midpoint distance | B10: =ABS(B9) -> 0.26074181 | C10: USD/share | D10: CP-14 threshold is $0.50
A11: Within supported range? | B11: =IF(AND(B8>=B5,B8<=B7),"Yes","No") -> Yes | C11: text | D11: CP-14/CP-15
A12: Within $0.50 of midpoint? | B12: =IF(B10<=0.5,"Yes","No") -> Yes | C12: text | D12: CP-14/CP-15
A13: Unresolved structure hard errors | B13: =COUNTIF(Error_Audit!E2:E15,"<>Corrected") -> 0 | C13: count | D13: All legacy structure errors corrected in this model
A14: Base company gross proceeds | B14: =Offering_Proceeds!B6 -> 519.40192 | C14: USD mm | D14: Primary only
A15: Base company net proceeds | B15: =Offering_Proceeds!B10 -> 486.43182 | C15: USD mm | D15: After percentage fee and fixed expenses
A16: Base post-money shares | B16: =Dilution!B5 -> 158.99309 | C16: mm shares | D16: Secondary excluded
A17: Full-exercise post-money shares | B17: =Dilution!C5 -> 162.29309 | C17: mm shares | D17: Separate scenario
A18: Recommendation | B18: =IF(AND(B11="Yes",B12="Yes",B13=0),"Proceed",IF(AND(B11="Yes",B13=0),"Reprice","Defer")) -> Proceed | C18: text | D18: Mechanical CP-14/CP-15 result

Sheet Error_Audit
A1: Issue category | B1: Legacy treatment | C1: Correct treatment | D1: Quantified impact | E1: Status | F1: Policy / boundary
A2: QoE starting metric | B2: Management Adjusted EBITDA used as underwriting conclusion | C2: Reverse SBC addback; restructuring adjustment remains zero | D2: 2023 EBITDA reduced by 49.086 to -118.361 | E2: Corrected | F2: CP-03/CP-04
A3: Double counting | B3: Risk of adding restructuring again | C3: No second addback because management metric already reflects it | D3: Avoids 8.098 overstatement | E3: Corrected | F3: CP-04
A4: Valuation denominator | B4: 4.5x applied to 2023A Revenue | C4: Use 2024E Revenue = 2023A × (1 + committee growth) | D4: Mid EV increases by 795.989 | E4: Corrected | F4: CP-05/CP-06
A5: Execution discount | B5: No discount applied | C5: Apply 12.5% to peer-implied equity value/share | D5: Mid price reduced by $4.89 | E5: Corrected | F5: CP-09
A6: Net cash bridge | B6: Marketable securities omitted | C6: Add cash and marketable securities to EV | D6: Equity value restored by 811.946 | E6: Corrected | F6: CP-08
A7: Primary / secondary | B7: All 22.0m base shares treated as primary | C7: Separate primary and secondary | D7: Company gross overstatement avoided: 228.598 at proposed price | E7: Corrected | F7: CP-10
A8: Greenshoe in Base | B8: 3.3m option included in Base | C8: Base excludes option; full exercise shown separately | D8: Base shares avoid 3.300 premature increase | E8: Corrected | F8: CP-11
A9: Underwriting fee basis | B9: Fee charged on primary + secondary | C9: Company fee charged only on primary gross | D9: Base company fee overstatement avoided: 11.430 | E9: Corrected | F9: CP-12
A10: Post-money shares | B10: Secondary added to company shares | C10: Only newly issued primary shares increase company shares | D10: Denominator overstatement avoided: 6.723473 shares | E10: Corrected | F10: CP-10
A11: Company proceeds | B11: Secondary proceeds added to company cash | C11: Secondary proceeds go to selling holders | D11: Company proceeds overstatement avoided: 228.598 | E11: Corrected | F11: CP-10
A12: Dilution convention | B12: Post-money equity divided by pre-money shares | C12: Use consistent post-money share bridge; SEC $32.50 data only cross-checks | D12: Legacy dilution result is not usable | E12: Corrected | F12: SEC-02 boundary
... A15: Detail export status | B15: Duplicate 2022-08 and preliminary 2023-12 could be summed | C15: Use original/audited-final rows and reconcile to SEC totals | D15: Avoids 57.100 duplicate and 66.500 preliminary double count | E15: Corrected | F15: CP-02 / data dictionary

Sheet Source_Trace
A1: metric | B1: selected_value | C1: unit | D1: selected_source_id | E1: selected_source_file | F1: source_type | G1: competing_value | H1: competing_source | I1: disposition
A2: Information cut-off | B2: 2024-03-20 | C2: date | D2: SEC-04 | E2: sec_filings/SEC-04_s1a_a2_20240315_summary.md | F2: SEC public fact | G2: Post-cutoff results | H2: Excluded | I2: Use only information available before committee pricing on 2024-03-20
A3: Controlling policy | B3: v3 | C3: version | E3: committee/Committee_Policy_v3_20240320.xlsx | F3: Internal committee policy | G3: v2 | H3: committee/Committee_Policy_v2_20240305.xlsx | I3: v3 supersedes v2 for SBC, peer range, discount and fee basis
A4: 2023 Revenue | B4: 804.029 | C4: USD mm | D4: SEC-01 | E4: sec_filings/SEC-01_financials_extract.xlsx | F4: SEC public fact | G4: 806.2 | H4: internal/management_flash_20240319.csv (INT-01, Priority 9) | I4: Use audited SEC-01; reject unreviewed flash
A5: 2023 Net income (loss) | B5: -90.824 | C5: USD mm | D5: SEC-01 | E5: sec_filings/SEC-01_financials_extract.xlsx | F5: SEC public fact | I5: Use SEC-01
A6: 2023 Management Adjusted EBITDA | B6: -69.275 | C6: USD mm | D6: SEC-01 | E6: sec_filings/SEC-01_financials_extract.xlsx | F6: SEC public non-GAAP fact | G6: -66.1 | H6: internal/management_flash_20240319.csv (INT-01, Priority 9) | I6: Use SEC-01; metric is outside auditor opinion
A7: 2023 SBC & related taxes | B7: 49.086 | C7: USD mm | D7: SEC-01 | E7: sec_filings/SEC-01_financials_extract.xlsx | F7: SEC public fact | G7: 47.3 | H7: internal/management_flash_20240319.csv (INT-01, Priority 9) | I7: Use SEC-01 and verified detail; reject flash
A8: 2023 Restructuring costs | B8: 8.098 | C8: USD mm | D8: SEC-01 | E8: financials/restructuring_detail_2023.csv | F8: SEC public fact/detail | G8: Possible second addback | H8: legacy treatment risk | I8: No second addback under CP-04
A9: 2023 Underwriting EBITDA | B9: -118.361 | C9: USD mm | D9: SEC-01 | E9: SEC-01 + committee/Committee_Policy_v3_20240320.xlsx | F9: Calculated underwriting convention | G9: -69.275 | H9: Legacy used management metric directly | I9: Reverse SBC addback under CP-03
A10: 2023 Free Cash Flow | B10: -84.838 | C10: USD mm | D10: SEC-01 | E10: sec_filings/SEC-01_financials_extract.xlsx | F10: SEC public non-GAAP fact | G10: -82.4 | H10: internal/management_flash_20240319.csv (INT-01, Priority 9) | I10: Use SEC-01; independently ties to OCF plus capex
A11: 2023 Cash & cash equivalents | B11: 401.176 | C11: USD mm | D11: SEC-01 | E11: sec_filings/SEC-01_financials_extract.xlsx | F11: SEC public fact | I11: Include in net cash bridge
A12: 2023 Marketable securities | B12: 811.946 | C12: USD mm | D12: SEC-01 | E12: sec_filings/SEC-01_financials_extract.xlsx | F12: SEC public fact | G12: Excluded | H12: legacy/Candidate_Model_v0.xlsx | I12: Include in net cash bridge under CP-08
A13: 2024E Revenue growth | B13: 0.22 | C13: % | D13: UW-01 | E13: committee/Underwriting_Assumptions_20240320.xlsx | F13: Internal committee assumption | G13: 18% sector median | H13: research/sector_benchmark.md | I13: Use 22.0% CP-06; do not present as SEC fact
A14: 2024E Revenue | B14: 980.91538 | C14: USD mm | D14: SEC-01 | E14: SEC-01 revenue × committee CP-06 growth | F14: Calculated using public fact + internal assumption | G14: 804.029 | H14: legacy used 2023A denominator | I14: Use forward revenue
A15: Peer Low / Mid / High | B15: 4.0x / 4.5x / 5.0x | C15: x | D15: UW-01 | E15: committee/Committee_Policy_v3_20240320.xlsx | F15: Internal committee assumption | G15: A 4.0-5.0x; B 4.2-5.1x | H15: comps files, Priority 8 | I15: Use committee range under CP-07; banks are cross-check only
A16: Execution discount | B16: 0.125 | C16: % | D16: UW-01 | E16: committee/Underwriting_Assumptions_20240320.xlsx | F16: Internal committee assumption | G16: 10% | H16: superseded Committee Policy v2 | I16: Use 12.5%; apply to implied equity value/share
A17: Pre-money economic shares | B17: 143.71656 | C17: mm shares | D17: SEC-09 | E17: committee/cap_table_snapshot_20240318.csv | F17: Internal committee snapshot using SEC-09 components | G17: 141.2 | H17: sec_filings/SEC-16_share_count_history.csv | I17: Use economic snapshot; registered count excludes unsettled RSUs
A18: Proposed price | B18: 34 | C18: USD/share | E18: committee/Offering_Terms_20240320.xlsx | F18: Internal committee assumption | G18: 31-34 | H18: SEC-03 preliminary filing range | I18: Decision input, not actual final price
A19: Base primary shares | B19: 15.276527 | C19: mm shares | D19: SEC-03 | E19: sec_filings/SEC-03_offering_terms.xlsx | F19: SEC public fact | G19: 22 | H19: legacy treated all base shares as primary | I19: Use SEC-03 primary amount
A20: Base secondary shares | B20: 6.723473 | C20: mm shares | D20: SEC-03 | E20: sec_filings/SEC-03_offering_terms.xlsx | F20: SEC public fact | G20: Included in company proceeds/share count | H20: legacy/Candidate_Model_v0.xlsx | I20: No company proceeds and no new company shares
A21: Greenshoe | B21: 3.3 | C21: mm shares | D21: SEC-03 | E21: sec_filings/SEC-03_offering_terms.xlsx | F21: SEC public fact | G21: Included in Base | H21: legacy/Candidate_Model_v0.xlsx | I21: Exclude from Base; show full-exercise separately
A22: Underwriting fee rate / basis | B22: 0.05 | C22: % of primary gross | D22: SEC-10 | E22: committee/Offering_Terms_20240320.xlsx; sec_filings/SEC-10_underwriting_agreement_summary.md | F22: SEC mechanism + internal rate assumption | G22: % of primary + secondary | H22: superseded Committee Policy v2 / legacy | I22: Apply to company primary gross only
A23: Fixed company expenses | B23: 7 | C23: USD mm | E23: committee/Offering_Terms_20240320.xlsx | F23: Internal committee assumption | G23: Repeated on greenshoe | H23: legacy risk | I23: Charge once in each total scenario; no repeat on increment
A24: SEC NTBV/share cross-check | B24: 11.17 | C24: USD/share | D24: SEC-02 | E24: sec_filings/SEC-02_dilution_crosscheck.xlsx | F24: SEC public fact at assumed price | G24: Not comparable directly to $34.00 | H24: Assumed price differs | I24: Use only as independent arithmetic/methodology boundary
A25: SEC immediate dilution cross-check | B25: 21.33 | C25: USD/share | D25: SEC-02 | E25: sec_filings/SEC-02_dilution_crosscheck.xlsx | F25: SEC public fact at assumed price | G25: Not comparable directly to $34.00 | H25: Assumed price differs | I25: 11.17 + 21.33 = 32.50; do not transplant to $34.00
A26: Committee supported range | B26: 31.27-37.25 | C26: USD/share | E26: Calculated from SEC-01 and committee policy v3 | F26: Calculated conclusion | G26: 31-34 | H26: SEC-03 preliminary filing range | I26: Committee range is valuation output; SEC range is execution cross-check
A27: Recommendation | B27: Proceed | C27: text | E27: committee/Committee_Policy_v3_20240320.xlsx | F27: Calculated policy disposition | G27: Legacy above $34.00 | H27: legacy/Candidate_Model_v0.xlsx | I27: Apply CP-14/CP-15 after correcting hard errors
